Workbook

Sheet Обложка
B3: ForkWork
B4: Юнит-экономика v2 — вычисляемая модель
B6: Принцип: ни одной экспертной константы в результатах.
B7: LTV, CAC, take-rate и окупаемость района выводятся формулами из листа «Допущения».
B9: Синяя ячейка = ввод (меняйте). Белая = формула (не трогать).
B11: Листы: Допущения → Выручка на заказ → CAC → Когорты LTV → Юнит-экономика → Экономика района → Чувствительность
B13: Дисклеймер: модель иллюстративная, для планирования пилота; факты пилота заменят допущения.

Sheet Допущения
A1: Допущения — единственный источник ввода
A2: Каждое число ниже имеет обоснование в колонке D; всё остальное в книге — формулы
B4: СПРОС И ПОВЕДЕНИЕ КЛИЕНТА
B5: Средний чек (AOV), ₽ | C5: 1250 | D5: Средний между «обед на одного» (~600) и «ужин на семью» (~2000); проверяется пилотом
B6: Заказов в месяц на активного клиента | C6: 2.4 | D6: Еда — частотная категория: 2–3 заказа/мес у нишевых фуд-сервисов; консервативно ниже агрегаторов (4–6)
B7: Удержание: доля месяца 2 (M2) | C7: 0.86 | D7: Геометрический спад: каждый месяц остаётся 86% от предыдущего — до пола
B8: Удержание: пол (лояльное ядро) | C8: 0.2 | D8: 20% становятся постоянными («свой повар») — эффект локальной привычки
B9: Горизонт LTV, месяцев | C9: 24 | D9: Стандартный горизонт для маркетплейсов на seed-стадии
B11: ВЫРУЧКА ПЛАТФОРМЫ (по потокам)
B12: Комиссия с заказа | C12: 0.1 | D12: Зафиксирована в продукте (PLATFORM_FEE=0.1) — козырь против 25–35% агрегаторов
B13: SaaS-подписка повара, ₽/мес | C13: 9900 | D13: Тариф «Профи»: аналитика, продвижение, записи эфиров
B14: Заказов на повара в месяц | C14: 160 | D14: 5–6 заказов/день на активного повара — уровень занятости «частичный день»
B15: Featured-размещения, ₽/мес на повара | C15: 2500 | D15: Средний расход повара на буст карточки/эфира
B16: Премиум-подписка клиента, ₽/мес | C16: 399 | D16: Бесплатная доставка + ранний доступ к эфирам
B17: Доля клиентов на премиуме | C17: 0.08 | D17: Консервативно: у зрелых сервисов 10–15%
B19: ПЕРЕМЕННЫЕ ЗАТРАТЫ НА ЗАКАЗ
B20: Эквайринг, % от чека | C20: 0.026 | D20: Ставка интернет-эквайринга ЮKassa/CloudPayments для малого бизнеса
B21: Поддержка и операции, ₽/заказ | C21: 12 | D21: Амортизация саппорта: 1 обращение на ~25 заказов × себестоимость обращения ~300 ₽
B22: Доля менеджера района от комиссии | C22: 0.1 | D22: Мотивация менеджера-партнёра — платится из комиссии платформы
B24: CAC ПО КАНАЛАМ (веса и параметры)
B25: Таргет (VK/Директ): CPC, ₽ | C25: 28 | D25: Средний CPC фуд-тематики в городах-миллионниках
B26: Таргет: конверсия клик → регистрация | C26: 0.07 | D26: Посадочная с живым эфиром; бенчмарк лендингов еды 5–10%
B27: Таргет: конверсия регистрация → 1-й заказ | C27: 0.38 | D27: Приветственные 500 FC снижают порог первого заказа
B28: Рефералка: бонус обоим, ₽ (2×300 FC) | C28: 600 | D28: Начисляется после первого заказа приглашённого — не тратится вхолостую
B29: Рефералка: доля дошедших до заказа | C29: 0.85 | D29: Бонус привязан к заказу, поэтому активация высокая
B30: Посевы в районе: бюджет, ₽/мес | C30: 40000 | D30: Районные чаты, листовки с QR, дегустации у поваров
B31: Посевы: новых клиентов в месяц | C31: 55 | D31: Оценка по охвату районных сообществ (5–15 тыс. человек)
B32: SEO-контент: бюджет, ₽/мес | C32: 18000 | D32: Амортизация производства рецептов-посадочных (делает Claude)
B33: SEO: новых клиентов в месяц | C33: 120 | D33: После индексации 100+ рецептов; маржинальная стоимость → 0
B34: Веса каналов: таргет / рефералка / посевы / SEO | C34: 30/25/25/20 | D34: Структура привлечения на этапе пилота
B35: Вес: таргет | C35: 0.3
B36: Вес: рефералка | C36: 0.25
B37: Вес: посевы | C37: 0.25
B38: Вес: SEO | C38: 0.2
B39: Накладные на привлечение (аналитика, инструменты) | C39: 0.12 | D39: Надбавка к смешанному CAC
B41: ЭКОНОМИКА РАЙОНА
B42: Целевые заказы/день района (плато) | C42: 40 | D42: 10 поваров × 4–6 заказов/день = целевая загрузка района
B43: Месяцев до плато | C43: 6 | D43: S-образный разгон: посевы + сарафан + эфиры
B44: Маркетинг района, ₽/мес | C44: 55000 | D44: Посевы 40к + доля таргета 15к

Sheet Выручка на заказ
A1: Выручка и вклад на один заказ
A2: Take-rate здесь — результат, а не допущение
B4: ВЫРУЧКА ПЛАТФОРМЫ НА ЗАКАЗ
B5: Комиссия с заказа, ₽ | C5: ='Допущения'!$C$5*'Допущения'!$C$12 | D5: AOV × комиссия
B6: SaaS на заказ, ₽ | C6: ='Допущения'!$C$13/'Допущения'!$C$14 | D6: подписка повара / его заказы в месяц
B7: Featured на заказ, ₽ | C7: ='Допущения'!$C$15/'Допущения'!$C$14 | D7: буст-бюджет повара / его заказы
B8: Премиум на заказ, ₽ | C8: ='Допущения'!$C$17*'Допущения'!$C$16/'Допущения'!$C$6 | D8: доля премиум-клиентов × цена / заказы клиента в месяц
B9: ИТОГО выручка платформы на заказ, ₽ | C9: =SUM(C5:C8)
B10: Эффективный take-rate (вычислен) | C10: =C9/'Допущения'!$C$5 | D10: ранее в модели была экспертная константа 18,55% — теперь считается
B12: ПЕРЕМЕННЫЕ ЗАТРАТЫ НА ЗАКАЗ
B13: Эквайринг, ₽ | C13: ='Допущения'!$C$5*'Допущения'!$C$20
B14: Поддержка и операции, ₽ | C14: ='Допущения'!$C$21
B15: Доля менеджера района, ₽ | C15: ='Допущения'!$C$5*'Допущения'!$C$12*'Допущения'!$C$22
B16: ИТОГО затраты на заказ, ₽ | C16: =SUM(C13:C15)
B18: ВКЛАД (contribution) на заказ, ₽ | C18: =C9-C16
B19: Маржа платформы от своей выручки | C19: =C18/C9

Sheet CAC
A1: Стоимость привлечения клиента — по каналам
A2: Смешанный CAC = взвешенная сумма каналов + накладные
B4: СТОИМОСТЬ КАНАЛОВ
B5: Таргет: CAC, ₽ | C5: ='Допущения'!$C$25/('Допущения'!$C$26*'Допущения'!$C$27) | D5: CPC / (CR клик→рег × CR рег→заказ)
B6: Рефералка: CAC, ₽ | C6: ='Допущения'!$C$28/'Допущения'!$C$29 | D6: бонусы / доля активации
B7: Посевы района: CAC, ₽ | C7: ='Допущения'!$C$30/'Допущения'!$C$31 | D7: бюджет / приведённые клиенты
B8: SEO-контент: CAC, ₽ | C8: ='Допущения'!$C$32/'Допущения'!$C$33 | D8: бюджет контента / клиенты из поиска
B10: СМЕШАННЫЙ CAC
B11: Взвешенный CAC, ₽ | C11: =C5*'Допущения'!$C$35+C6*'Допущения'!$C$36+C7*'Допущения'!$C$37+C8*'Допущения'!$C$38
B12: CAC с накладными, ₽ | C12: =C11*(1+'Допущения'!$C$39)

Sheet Когорты LTV
A1: Когорта из 100 клиентов на горизонте 24 месяцев
A2: Retention: M1=100%, далее ×decay до пола; LTV = накопленный вклад на клиента
B4: Месяц | C4: Retention | D4: Активных из 100 | E4: Заказов | F4: Вклад когорты, ₽ | G4: LTV накопл., ₽/клиент
B5: 1 | C5: 1 | D5: =100*C5 | E5: =D5*'Допущения'!$C$6 | F5: =E5*'Выручка на заказ'!$C$18 | G5: =F5/100
B6: 2 | C6: =MAX('Допущения'!$C$8,C5*'Допущения'!$C$7) | D6: =100*C6 | E6: =D6*'Допущения'!$C$6 | F6: =E6*'Выручка на заказ'!$C$18 | G6: =G5+F6/100
B7: 3 | C7: =MAX('Допущения'!$C$8,C6*'Допущения'!$C$7) | D7: =100*C7 | E7: =D7*'Допущения'!$C$6 | F7: =E7*'Выручка на заказ'!$C$18 | G7: =G6+F7/100
B8: 4 | C8: =MAX('Допущения'!$C$8,C7*'Допущения'!$C$7) | D8: =100*C8 | E8: =D8*'Допущения'!$C$6 | F8: =E8*'Выручка на заказ'!$C$18 | G8: =G7+F8/100
B9: 5 | C9: =MAX('Допущения'!$C$8,C8*'Допущения'!$C$7) | D9: =100*C9 | E9: =D9*'Допущения'!$C$6 | F9: =E9*'Выручка на заказ'!$C$18 | G9: =G8+F9/100
B10: 6 | C10: =MAX('Допущения'!$C$8,C9*'Допущения'!$C$7) | D10: =100*C10 | E10: =D10*'Допущения'!$C$6 | F10: =E10*'Выручка на заказ'!$C$18 | G10: =G9+F10/100
B11: 7 | C11: =MAX('Допущения'!$C$8,C10*'Допущения'!$C$7) | D11: =100*C11 | E11: =D11*'Допущения'!$C$6 | F11: =E11*'Выручка на заказ'!$C$18 | G11: =G10+F11/100
B12: 8 | C12: =MAX('Допущения'!$C$8,C11*'Допущения'!$C$7) | D12: =100*C12 | E12: =D12*'Допущения'!$C$6 | F12: =E12*'Выручка на заказ'!$C$18 | G12: =G11+F12/100
B13: 9 | C13: =MAX('Допущения'!$C$8,C12*'Допущения'!$C$7) | D13: =100*C13 | E13: =D13*'Допущения'!$C$6 | F13: =E13*'Выручка на заказ'!$C$18 | G13: =G12+F13/100
B14: 10 | C14: =MAX('Допущения'!$C$8,C13*'Допущения'!$C$7) | D14: =100*C14 | E14: =D14*'Допущения'!$C$6 | F14: =E14*'Выручка на заказ'!$C$18 | G14: =G13+F14/100
B15: 11 | C15: =MAX('Допущения'!$C$8,C14*'Допущения'!$C$7) | D15: =100*C15 | E15: =D15*'Допущения'!$C$6 | F15: =E15*'Выручка на заказ'!$C$18 | G15: =G14+F15/100
B16: 12 | C16: =MAX('Допущения'!$C$8,C15*'Допущения'!$C$7) | D16: =100*C16 | E16: =D16*'Допущения'!$C$6 | F16: =E16*'Выручка на заказ'!$C$18 | G16: =G15+F16/100
B17: 13 | C17: =MAX('Допущения'!$C$8,C16*'Допущения'!$C$7) | D17: =100*C17 | E17: =D17*'Допущения'!$C$6 | F17: =E17*'Выручка на заказ'!$C$18 | G17: =G16+F17/100
... B28: 24 | C28: =MAX('Допущения'!$C$8,C27*'Допущения'!$C$7) | D28: =100*C28 | E28: =D28*'Допущения'!$C$6 | F28: =E28*'Выручка на заказ'!$C$18 | G28: =G27+F28/100
B30: LTV на горизонте 24 мес, ₽/клиент | C30: =G28
B31: Месячный вклад активного клиента, ₽ | C31: ='Допущения'!$C$6*'Выручка на заказ'!$C$18

Sheet Юнит-экономика
A1: Сводка юнит-экономики
A2: Все значения — формулы; изменение любого допущения пересчитывает всё
B4: КЛЮЧЕВЫЕ ПОКАЗАТЕЛИ
B5: AOV, ₽ | C5: ='Допущения'!$C$5
B6: Выручка платформы на заказ, ₽ | C6: ='Выручка на заказ'!$C$9
B7: Эффективный take-rate | C7: ='Выручка на заказ'!$C$10
B8: Вклад на заказ, ₽ | C8: ='Выручка на заказ'!$C$18
B9: LTV (24 мес), ₽ | C9: ='Когорты LTV'!$C$30
B10: CAC (смешанный), ₽ | C10: ='CAC'!$C$12
B11: LTV / CAC | C11: ='Когорты LTV'!$C$30/'CAC'!$C$12
B12: Окупаемость клиента (payback) | C12: ='CAC'!$C$12/'Когорты LTV'!$C$31
B14: Критерии здоровья: LTV/CAC > 3× — хорошо; payback < 6 мес — хорошо.

Sheet Экономика района
A1: Район как юнит масштабирования
A2: S-образный разгон до плато; когда район выходит в плюс
B4: Месяц | C4: Заказов/день | D4: Заказов/мес | E4: Вклад, ₽/мес | F4: Маркетинг, ₽/мес | G4: Прибыль района, ₽ | H4: Накопленно, ₽
B5: 1 | C5: ='Допущения'!$C$42*B5^2/(B5^2+('Допущения'!$C$43/2)^2) | D5: =C5*30 | E5: =D5*'Выручка на заказ'!$C$18 | F5: ='Допущения'!$C$44 | G5: =E5-F5 | H5: =G5
B6: 2 | C6: ='Допущения'!$C$42*B6^2/(B6^2+('Допущения'!$C$43/2)^2) | D6: =C6*30 | E6: =D6*'Выручка на заказ'!$C$18 | F6: ='Допущения'!$C$44 | G6: =E6-F6 | H6: =H5+G6
B7: 3 | C7: ='Допущения'!$C$42*B7^2/(B7^2+('Допущения'!$C$43/2)^2) | D7: =C7*30 | E7: =D7*'Выручка на заказ'!$C$18 | F7: ='Допущения'!$C$44 | G7: =E7-F7 | H7: =H6+G7
B8: 4 | C8: ='Допущения'!$C$42*B8^2/(B8^2+('Допущения'!$C$43/2)^2) | D8: =C8*30 | E8: =D8*'Выручка на заказ'!$C$18 | F8: ='Допущения'!$C$44 | G8: =E8-F8 | H8: =H7+G8
B9: 5 | C9: ='Допущения'!$C$42*B9^2/(B9^2+('Допущения'!$C$43/2)^2) | D9: =C9*30 | E9: =D9*'Выручка на заказ'!$C$18 | F9: ='Допущения'!$C$44 | G9: =E9-F9 | H9: =H8+G9
B10: 6 | C10: ='Допущения'!$C$42*B10^2/(B10^2+('Допущения'!$C$43/2)^2) | D10: =C10*30 | E10: =D10*'Выручка на заказ'!$C$18 | F10: ='Допущения'!$C$44 | G10: =E10-F10 | H10: =H9+G10
B11: 7 | C11: ='Допущения'!$C$42*B11^2/(B11^2+('Допущения'!$C$43/2)^2) | D11: =C11*30 | E11: =D11*'Выручка на заказ'!$C$18 | F11: ='Допущения'!$C$44 | G11: =E11-F11 | H11: =H10+G11
B12: 8 | C12: ='Допущения'!$C$42*B12^2/(B12^2+('Допущения'!$C$43/2)^2) | D12: =C12*30 | E12: =D12*'Выручка на заказ'!$C$18 | F12: ='Допущения'!$C$44 | G12: =E12-F12 | H12: =H11+G12
B13: 9 | C13: ='Допущения'!$C$42*B13^2/(B13^2+('Допущения'!$C$43/2)^2) | D13: =C13*30 | E13: =D13*'Выручка на заказ'!$C$18 | F13: ='Допущения'!$C$44 | G13: =E13-F13 | H13: =H12+G13
B14: 10 | C14: ='Допущения'!$C$42*B14^2/(B14^2+('Допущения'!$C$43/2)^2) | D14: =C14*30 | E14: =D14*'Выручка на заказ'!$C$18 | F14: ='Допущения'!$C$44 | G14: =E14-F14 | H14: =H13+G14
B15: 11 | C15: ='Допущения'!$C$42*B15^2/(B15^2+('Допущения'!$C$43/2)^2) | D15: =C15*30 | E15: =D15*'Выручка на заказ'!$C$18 | F15: ='Допущения'!$C$44 | G15: =E15-F15 | H15: =H14+G15
B16: 12 | C16: ='Допущения'!$C$42*B16^2/(B16^2+('Допущения'!$C$43/2)^2) | D16: =C16*30 | E16: =D16*'Выручка на заказ'!$C$18 | F16: ='Допущения'!$C$44 | G16: =E16-F16 | H16: =H15+G16
B18: Прибыль района на плато, ₽/мес | C18: =G16
B19: Месяц выхода в операционный плюс | C19: =MATCH(TRUE,INDEX(G5:G16>0,0),0)

Sheet Чувствительность
A1: LTV/CAC при разных удержании и чеке
A2: Сетка формул: строки — retention decay, столбцы — AOV
B4: Помощник: Σ retention (24 мес) | AB4: Σ
B5: 0.8 | C5: 1 | D5: =MAX('Допущения'!$C$8,C5*$B$5) | E5: =MAX('Допущения'!$C$8,D5*$B$5) | F5: =MAX('Допущения'!$C$8,E5*$B$5) | G5: =MAX('Допущения'!$C$8,F5*$B$5) | H5: =MAX('Допущения'!$C$8,G5*$B$5) | I5: =MAX('Допущения'!$C$8,H5*$B$5) | J5: =MAX('Допущения'!$C$8,I5*$B$5) | K5: =MAX('Допущения'!$C$8,J5*$B$5) | ... Z5: =MAX('Допущения'!$C$8,Y5*$B$5) | AB5: =SUM(C5:AA5)
B6: 0.83 | C6: 1 | D6: =MAX('Допущения'!$C$8,C6*$B$6) | E6: =MAX('Допущения'!$C$8,D6*$B$6) | F6: =MAX('Допущения'!$C$8,E6*$B$6) | G6: =MAX('Допущения'!$C$8,F6*$B$6) | H6: =MAX('Допущения'!$C$8,G6*$B$6) | I6: =MAX('Допущения'!$C$8,H6*$B$6) | J6: =MAX('Допущения'!$C$8,I6*$B$6) | K6: =MAX('Допущения'!$C$8,J6*$B$6) | ... Z6: =MAX('Допущения'!$C$8,Y6*$B$6) | AB6: =SUM(C6:AA6)
B7: 0.86 | C7: 1 | D7: =MAX('Допущения'!$C$8,C7*$B$7) | E7: =MAX('Допущения'!$C$8,D7*$B$7) | F7: =MAX('Допущения'!$C$8,E7*$B$7) | G7: =MAX('Допущения'!$C$8,F7*$B$7) | H7: =MAX('Допущения'!$C$8,G7*$B$7) | I7: =MAX('Допущения'!$C$8,H7*$B$7) | J7: =MAX('Допущения'!$C$8,I7*$B$7) | K7: =MAX('Допущения'!$C$8,J7*$B$7) | ... Z7: =MAX('Допущения'!$C$8,Y7*$B$7) | AB7: =SUM(C7:AA7)
B8: 0.89 | C8: 1 | D8: =MAX('Допущения'!$C$8,C8*$B$8) | E8: =MAX('Допущения'!$C$8,D8*$B$8) | F8: =MAX('Допущения'!$C$8,E8*$B$8) | G8: =MAX('Допущения'!$C$8,F8*$B$8) | H8: =MAX('Допущения'!$C$8,G8*$B$8) | I8: =MAX('Допущения'!$C$8,H8*$B$8) | J8: =MAX('Допущения'!$C$8,I8*$B$8) | K8: =MAX('Допущения'!$C$8,J8*$B$8) | ... Z8: =MAX('Допущения'!$C$8,Y8*$B$8) | AB8: =SUM(C8:AA8)
B9: 0.92 | C9: 1 | D9: =MAX('Допущения'!$C$8,C9*$B$9) | E9: =MAX('Допущения'!$C$8,D9*$B$9) | F9: =MAX('Допущения'!$C$8,E9*$B$9) | G9: =MAX('Допущения'!$C$8,F9*$B$9) | H9: =MAX('Допущения'!$C$8,G9*$B$9) | I9: =MAX('Допущения'!$C$8,H9*$B$9) | J9: =MAX('Допущения'!$C$8,I9*$B$9) | K9: =MAX('Допущения'!$C$8,J9*$B$9) | ... Z9: =MAX('Допущения'!$C$8,Y9*$B$9) | AB9: =SUM(C9:AA9)
B12: LTV / CAC | C12: 1000 | D12: 1250 | E12: 1500
B13: 0.8 | C13: ='Допущения'!$C$6*(C12*'Допущения'!$C$12+'Допущения'!$C$13/'Допущения'!$C$14+'Допущения'!$C$15/'Допущения'!$C$14+'Допущения'!$C$17*'Допущения'!$C$16/'Допущения'!$C$6-C12*'Допущения'!$C$20-'Допущения'!$C$21-C12*'Допущения'!$C$12*'Допущения'!$C$22)*$AB$5/'CAC'!$C$12 | D13: ='Допущения'!$C$6*(D12*'Допущения'!$C$12+'Допущения'!$C$13/'Допущения'!$C$14+'Допущения'!$C$15/'Допущения'!$C$14+'Допущения'!$C$17*'Допущения'!$C$16/'Допущения'!$C$6-D12*'Допущения'!$C$20-'Допущения'!$C$21-D12*'Допущения'!$C$12*'Допущения'!$C$22)*$AB$5/'CAC'!$C$12 | E13: ='Допущения'!$C$6*(E12*'Допущения'!$C$12+'Допущения'!$C$13/'Допущения'!$C$14+'Допущения'!$C$15/'Допущения'!$C$14+'Допущения'!$C$17*'Допущения'!$C$16/'Допущения'!$C$6-E12*'Допущения'!$C$20-'Допущения'!$C$21-E12*'Допущения'!$C$12*'Допущения'!$C$22)*$AB$5/'CAC'!$C$12
B14: 0.83 | C14: ='Допущения'!$C$6*(C12*'Допущения'!$C$12+'Допущения'!$C$13/'Допущения'!$C$14+'Допущения'!$C$15/'Допущения'!$C$14+'Допущения'!$C$17*'Допущения'!$C$16/'Допущения'!$C$6-C12*'Допущения'!$C$20-'Допущения'!$C$21-C12*'Допущения'!$C$12*'Допущения'!$C$22)*$AB$6/'CAC'!$C$12 | D14: ='Допущения'!$C$6*(D12*'Допущения'!$C$12+'Допущения'!$C$13/'Допущения'!$C$14+'Допущения'!$C$15/'Допущения'!$C$14+'Допущения'!$C$17*'Допущения'!$C$16/'Допущения'!$C$6-D12*'Допущения'!$C$20-'Допущения'!$C$21-D12*'Допущения'!$C$12*'Допущения'!$C$22)*$AB$6/'CAC'!$C$12 | E14: ='Допущения'!$C$6*(E12*'Допущения'!$C$12+'Допущения'!$C$13/'Допущения'!$C$14+'Допущения'!$C$15/'Допущения'!$C$14+'Допущения'!$C$17*'Допущения'!$C$16/'Допущения'!$C$6-E12*'Допущения'!$C$20-'Допущения'!$C$21-E12*'Допущения'!$C$12*'Допущения'!$C$22)*$AB$6/'CAC'!$C$12
B15: 0.86 | C15: ='Допущения'!$C$6*(C12*'Допущения'!$C$12+'Допущения'!$C$13/'Допущения'!$C$14+'Допущения'!$C$15/'Допущения'!$C$14+'Допущения'!$C$17*'Допущения'!$C$16/'Допущения'!$C$6-C12*'Допущения'!$C$20-'Допущения'!$C$21-C12*'Допущения'!$C$12*'Допущения'!$C$22)*$AB$7/'CAC'!$C$12 | D15: ='Допущения'!$C$6*(D12*'Допущения'!$C$12+'Допущения'!$C$13/'Допущения'!$C$14+'Допущения'!$C$15/'Допущения'!$C$14+'Допущения'!$C$17*'Допущения'!$C$16/'Допущения'!$C$6-D12*'Допущения'!$C$20-'Допущения'!$C$21-D12*'Допущения'!$C$12*'Допущения'!$C$22)*$AB$7/'CAC'!$C$12 | E15: ='Допущения'!$C$6*(E12*'Допущения'!$C$12+'Допущения'!$C$13/'Допущения'!$C$14+'Допущения'!$C$15/'Допущения'!$C$14+'Допущения'!$C$17*'Допущения'!$C$16/'Допущения'!$C$6-E12*'Допущения'!$C$20-'Допущения'!$C$21-E12*'Допущения'!$C$12*'Допущения'!$C$22)*$AB$7/'CAC'!$C$12
B16: 0.89 | C16: ='Допущения'!$C$6*(C12*'Допущения'!$C$12+'Допущения'!$C$13/'Допущения'!$C$14+'Допущения'!$C$15/'Допущения'!$C$14+'Допущения'!$C$17*'Допущения'!$C$16/'Допущения'!$C$6-C12*'Допущения'!$C$20-'Допущения'!$C$21-C12*'Допущения'!$C$12*'Допущения'!$C$22)*$AB$8/'CAC'!$C$12 | D16: ='Допущения'!$C$6*(D12*'Допущения'!$C$12+'Допущения'!$C$13/'Допущения'!$C$14+'Допущения'!$C$15/'Допущения'!$C$14+'Допущения'!$C$17*'Допущения'!$C$16/'Допущения'!$C$6-D12*'Допущения'!$C$20-'Допущения'!$C$21-D12*'Допущения'!$C$12*'Допущения'!$C$22)*$AB$8/'CAC'!$C$12 | E16: ='Допущения'!$C$6*(E12*'Допущения'!$C$12+'Допущения'!$C$13/'Допущения'!$C$14+'Допущения'!$C$15/'Допущения'!$C$14+'Допущения'!$C$17*'Допущения'!$C$16/'Допущения'!$C$6-E12*'Допущения'!$C$20-'Допущения'!$C$21-E12*'Допущения'!$C$12*'Допущения'!$C$22)*$AB$8/'CAC'!$C$12
B17: 0.92 | C17: ='Допущения'!$C$6*(C12*'Допущения'!$C$12+'Допущения'!$C$13/'Допущения'!$C$14+'Допущения'!$C$15/'Допущения'!$C$14+'Допущения'!$C$17*'Допущения'!$C$16/'Допущения'!$C$6-C12*'Допущения'!$C$20-'Допущения'!$C$21-C12*'Допущения'!$C$12*'Допущения'!$C$22)*$AB$9/'CAC'!$C$12 | D17: ='Допущения'!$C$6*(D12*'Допущения'!$C$12+'Допущения'!$C$13/'Допущения'!$C$14+'Допущения'!$C$15/'Допущения'!$C$14+'Допущения'!$C$17*'Допущения'!$C$16/'Допущения'!$C$6-D12*'Допущения'!$C$20-'Допущения'!$C$21-D12*'Допущения'!$C$12*'Допущения'!$C$22)*$AB$9/'CAC'!$C$12 | E17: ='Допущения'!$C$6*(E12*'Допущения'!$C$12+'Допущения'!$C$13/'Допущения'!$C$14+'Допущения'!$C$15/'Допущения'!$C$14+'Допущения'!$C$17*'Допущения'!$C$16/'Допущения'!$C$6-E12*'Допущения'!$C$20-'Допущения'!$C$21-E12*'Допущения'!$C$12*'Допущения'!$C$22)*$AB$9/'CAC'!$C$12
B19: Зелёная зона > 3×; базовый сценарий — центр сетки (decay 86%, AOV 1250).
